tmclient/__init__.py
tmclient/api.py
tmclient/auth.py
tmclient/base.py
tmclient/cli.py
tmclient/errors.py
tmclient/log.py
tmclient/version.py
tmclient-0.3.3.dist-info/DESCRIPTION.rst
tmclient-0.3.3.dist-info/METADATA
tmclient-0.3.3.dist-info/RECORD
tmclient-0.3.3.dist-info/WHEEL
tmclient-0.3.3.dist-info/entry_points.txt
tmclient-0.3.3.dist-info/metadata.json
tmclient-0.3.3.dist-info/pbr.json
tmclient-0.3.3.dist-info/top_level.txt
