Metadata-Version: 2.0
Name: tmclient
Version: 0.3.3
Summary: RESTful API client for TissueMAPS.
Home-page: https://github.com/tissuemaps/tmclient
Author: Markus D. Herrmann
Author-email: UNKNOWN
License: Apache-2.0
Platform: Linux
Platform: MacOS
Platform: Windows
Classifier: License :: OSI Approved :: Apache Software License
Classifier: Operating System :: MacOS
Classifier: Operating System :: Microsoft :: Windows
Classifier: Operating System :: POSIX :: Linux
Classifier: Intended Audience :: Science/Research
Classifier: Topic :: Scientific/Engineering :: Information Analysis
Classifier: Topic :: Scientific/Engineering :: Bio-Informatics
Classifier: Topic :: Internet :: WWW/HTTP
Classifier: Programming Language :: Python :: 2
Classifier: Programming Language :: Python :: 3
Classifier: Development Status :: 4 - Beta
Requires-Dist: PyYAML (>=3.11)
Requires-Dist: opencv-contrib-python (>=3.2)
Requires-Dist: pandas (>=0.19.1)
Requires-Dist: prettytable (>=0.7.2)
Requires-Dist: requests (>=2.11.0)
